odoo/addons/pos_payment_change/README.rst
odoo/addons/pos_payment_change/__init__.py
odoo/addons/pos_payment_change/__manifest__.py
odoo/addons/pos_payment_change/i18n/de.po
odoo/addons/pos_payment_change/i18n/es.po
odoo/addons/pos_payment_change/i18n/fr.po
odoo/addons/pos_payment_change/i18n/pos_payment_change.pot
odoo/addons/pos_payment_change/models/__init__.py
odoo/addons/pos_payment_change/models/pos_config.py
odoo/addons/pos_payment_change/models/pos_order.py
odoo/addons/pos_payment_change/readme/CONFIGURE.rst
odoo/addons/pos_payment_change/readme/CONTRIBUTORS.rst
odoo/addons/pos_payment_change/readme/CREDITS.rst
odoo/addons/pos_payment_change/readme/DESCRIPTION.rst
odoo/addons/pos_payment_change/readme/USAGE.rst
odoo/addons/pos_payment_change/static/description/icon.png
odoo/addons/pos_payment_change/static/description/index.html
odoo/addons/pos_payment_change/static/description/pos_config_form.png
odoo/addons/pos_payment_change/static/description/pos_order_form.png
odoo/addons/pos_payment_change/static/description/pos_order_tree.png
odoo/addons/pos_payment_change/static/description/pos_payment_change_wizard_form.png
odoo/addons/pos_payment_change/tests/__init__.py
odoo/addons/pos_payment_change/tests/test_module.py
odoo/addons/pos_payment_change/views/view_pos_config.xml
odoo/addons/pos_payment_change/views/view_pos_order.xml
odoo/addons/pos_payment_change/wizards/__init__.py
odoo/addons/pos_payment_change/wizards/pos_payment_change_wizard.py
odoo/addons/pos_payment_change/wizards/pos_payment_change_wizard_new_line.py
odoo/addons/pos_payment_change/wizards/pos_payment_change_wizard_old_line.py
odoo/addons/pos_payment_change/wizards/view_pos_payment_change_wizard.xml
odoo12_addon_pos_payment_change-12.0.1.1.1.dist-info/METADATA
odoo12_addon_pos_payment_change-12.0.1.1.1.dist-info/WHEEL
odoo12_addon_pos_payment_change-12.0.1.1.1.dist-info/top_level.txt
odoo12_addon_pos_payment_change-12.0.1.1.1.dist-info/RECORD
